datalake_common/__init__.py
datalake_common/errors.py
datalake_common/metadata.py
datalake_common/conf.py
datalake_common/_version.py
datalake_common/tests/__init__.py
datalake_common/tests/test_metadata.py
datalake_common/tests/test_conf.py
datalake_common/tests/conftest.py
datalake_common_dtkav-0.29.dist-info/RECORD
datalake_common_dtkav-0.29.dist-info/WHEEL
datalake_common_dtkav-0.29.dist-info/DESCRIPTION.rst
datalake_common_dtkav-0.29.dist-info/metadata.json
datalake_common_dtkav-0.29.dist-info/METADATA
datalake_common_dtkav-0.29.dist-info/top_level.txt
