Metadata-Version: 2.0
Name: datalake-common-dtkav
Version: 0.29
Summary: fork of planetlabs/datalake-common
Home-page: https://github.com/dtkav/datalake-common
Author: Daniel Grossmann-Kavanagh
Author-email: me@danielgk.com
License: UNKNOWN
Platform: UNKNOWN
Provides-Extra: test
Requires-Dist: python-dateutil (>=2.4.2)
Requires-Dist: pytz (>=2015.4)
Requires-Dist: simplejson (>=3.3.1)
Requires-Dist: python-dotenv (>=0.1.3)
Requires-Dist: six (>=1.10.0)
Provides-Extra: test
Requires-Dist: pytest (==3.0.2); extra == 'test'
Requires-Dist: pip (==7.1.0); extra == 'test'
Requires-Dist: wheel (==0.24.0); extra == 'test'
Requires-Dist: flake8 (==2.5.0); extra == 'test'
